tomni/__init__.py
tomni/annotation_manager/__init__.py
tomni/annotation_manager/main.py
tomni/annotation_manager/test_annotation_manager.py
tomni/annotation_manager/annotations/__init__.py
tomni/annotation_manager/annotations/annotation/__init__.py
tomni/annotation_manager/annotations/annotation/main.py
tomni/annotation_manager/annotations/binary_mask/__init__.py
tomni/annotation_manager/annotations/binary_mask/main.py
tomni/annotation_manager/annotations/ellipse/__init__.py
tomni/annotation_manager/annotations/ellipse/main.py
tomni/annotation_manager/annotations/ellipse/test_ellipse.py
tomni/annotation_manager/annotations/ellipse/test_ellipse_comparing.py
tomni/annotation_manager/annotations/point/__init__.py
tomni/annotation_manager/annotations/point/main.py
tomni/annotation_manager/annotations/point/test_point_comparing.py
tomni/annotation_manager/annotations/polygon/__init__.py
tomni/annotation_manager/annotations/polygon/main.py
tomni/annotation_manager/annotations/polygon/test_polygon.py
tomni/annotation_manager/annotations/polygon/test_polygon_comparing.py
tomni/annotation_manager/utils/__init__.py
tomni/annotation_manager/utils/main.py
tomni/annotation_manager/utils/test_utils.py
tomni/annotation_manager/utils/are_lines_equal/__init__.py
tomni/annotation_manager/utils/are_lines_equal/main.py
tomni/annotation_manager/utils/are_lines_equal/test_lines_equal.py
tomni/annotation_manager/utils/compress_polygon_points/__init__.py
tomni/annotation_manager/utils/compress_polygon_points/main.py
tomni/annotation_manager/utils/compress_polygon_points/test_compress_polygon_points.py
tomni/annotation_manager/utils/contours2polygons/__init__.py
tomni/annotation_manager/utils/contours2polygons/main.py
tomni/annotation_manager/utils/contours2polygons/test_contours2polygons.py
tomni/annotation_manager/utils/overlap_object/__init__.py
tomni/annotation_manager/utils/overlap_object/main.py
tomni/annotation_manager/utils/overlap_object/test_overlap_object.py
tomni-2.2.2.dist-info/METADATA
tomni-2.2.2.dist-info/WHEEL
tomni-2.2.2.dist-info/licenses/LICENSE
tomni-2.2.2.dist-info/RECORD
