Metadata-Version: 2.3
Name: tomni
Version: 2.2.2
Project-URL: Documentation, https://tomni.cytosmart.com/
Project-URL: Changelog, https://github.com/cytosmart-bv/tomni/blob/main/HISTORY.rst
Project-URL: Repository, https://github.com/cytosmart-bv/tomni
Author: Tom Nijhof, Jelle van Kerkvoorde
Author-email: Bram van der Velden <bram.vandervelden@axionbio.com>
License: Apache License
License-File: LICENSE
Keywords: checker,crlf,lf,line-ending
Classifier: Development Status :: 4 - Beta
Classifier: Environment :: Console
Classifier: Intended Audience :: Developers
Classifier: Intended Audience :: System Administrators
Classifier: License :: OSI Approved :: Apache Software License
Classifier: Operating System :: OS Independent
Classifier: Programming Language :: Python
Classifier: Programming Language :: Python :: 3
Classifier: Programming Language :: Python :: 3 :: Only
Classifier: Programming Language :: Python :: 3.7
Classifier: Programming Language :: Python :: 3.8
Classifier: Programming Language :: Python :: 3.9
Classifier: Programming Language :: Python :: 3.10
Classifier: Programming Language :: Python :: 3.11
Requires-Python: >=3.8
Requires-Dist: numpy-indexed<0.4,>=0.3.5
Requires-Dist: numpy<3,>=1.18.0
Requires-Dist: opencv-python-headless<4.11.0.0,>=4.3.0.38
Requires-Dist: scipy<2,>=1.4.1
Requires-Dist: shapely<3,>=1.8
Requires-Dist: simplification<1,>=0.6.11
Provides-Extra: test
Requires-Dist: black<25,>=24.4.2; extra == 'test'
Requires-Dist: pytest<9,>=8.3.1; extra == 'test'
